jgit/__init__.py
jgit/cli.py
jgit/is.py
jgit/metadata.py
jgit-0.2.3.data/data/bin/git-mod-add
jgit-0.2.3.data/data/bin/git-top
jgit-0.2.3.data/data/bin/jgit-src
jgit-0.2.3.dist-info/LICENSE
jgit-0.2.3.dist-info/METADATA
jgit-0.2.3.dist-info/WHEEL
jgit-0.2.3.dist-info/entry_points.txt
jgit-0.2.3.dist-info/top_level.txt
jgit-0.2.3.dist-info/RECORD
