Metadata-Version: 2.1
Name: jgit
Version: 0.2.3
Summary: UNKNOWN
License: UNKNOWN
Platform: UNKNOWN
Requires-Python: >=3.9
License-File: LICENSE
Provides-Extra: test
Requires-Dist: pytest ; extra == 'test'
